flask_mysql_connector/__init__.py
flask_mysql_connector/flask_mysql_connector.py
flask_mysql_connector/params.py
flask_mysql_connector-1.1.0.dist-info/LICENSE
flask_mysql_connector-1.1.0.dist-info/METADATA
flask_mysql_connector-1.1.0.dist-info/WHEEL
flask_mysql_connector-1.1.0.dist-info/top_level.txt
flask_mysql_connector-1.1.0.dist-info/RECORD
