Metadata-Version: 2.1
Name: flask_mysql_connector
Version: 1.1.0
Summary: Easy to use MySQL client for Flask apps.
Home-page: https://github.com/brandenc40/flask_mysql_connector
Author: Branden Colen
Author-email: brandencolen@gmail.com
License: MIT
Platform: any
Classifier: Environment :: Web Environment
Classifier: Intended Audience :: Developers
Classifier: Operating System :: OS Independent
Classifier: Programming Language :: Python
Classifier: Topic :: Internet :: WWW/HTTP :: Dynamic Content
Classifier: Topic :: Software Development :: Libraries :: Python Modules
Classifier: Programming Language :: Python :: 2
Classifier: Programming Language :: Python :: 3
